<chart palette='2' caption='2009年派出所调查活动方式分析' shownames='1' showvalues='0' decimals='0' numberPrefix='' useRoundEdges='1' legendBorderAlpha='0'>
<categories>
<category label='蛇口派出所' />
<category label='福永派出所' />
<category label='樟坑派出所' />
<category label='南头派出所' />
<category label='。。。派出所' />
</categories>
<dataset seriesName='网络' color='AFD8F8' showValues='0'>
<set value='25601' />
<set value='20148' />
<set value='17372' />
<set value='35407' />
<set value='38105' />
</dataset>
<dataset seriesName='系统' color='F6BD0F' showValues='0'>
<set value='57401' />
<set value='41941' />
<set value='45263' />
<set value='17320' />
<set value='14845' />
</dataset>
<dataset seriesName='短信' color='8BBA00' showValues='0'>
<set value='45000' />
<set value='44835' />
<set value='18722' />
<set value='77557' />
<set value='92633' />
</dataset>
<dataset seriesName='其他' color='8ABA7F' showValues='0'>
<set value='32400' />
<set value='32835' />
<set value='31122' />
<set value='72557' />
<set value='56633' />
</dataset>
</chart>