<?xml version="1.0" encoding="utf-8"?>
<!DOCTYPE hibernate-mapping PUBLIC "-//Hibernate/Hibernate Mapping DTD 3.0//EN"
"http://hibernate.sourceforge.net/hibernate-mapping-3.0.dtd">
<!-- 
    Mapping file autogenerated by MyEclipse Persistence Tools
-->
<hibernate-mapping>
    <class name="com.insigma.siis.local.business.entity.Attribute" table="Attribute" >
        <comment>id</comment>
        <id name="id" type="java.lang.String">
            <column name="id" length="60" />
            <generator class="assigned" />
        </id>
        <property name="a0000" type="java.lang.String">
            <column name="a0000" length="120">           
            </column>
        </property>
        <property name="sheng1" type="java.lang.String">
            <column name="sheng1" length="10">             
            </column>
        </property>
        <property name="sheng2" type="java.lang.String">
            <column name="sheng2" length="200">             
            </column>
        </property>
        <property name="sheng3" type="java.lang.String">
            <column name="sheng3" length="10">             
            </column>
        </property>
        <property name="sheng4" type="java.lang.String">
            <column name="sheng4" length="60">             
            </column>
        </property>
        <property name="sheng5" type="java.lang.String">
            <column name="sheng5" length="60">             
            </column>
        </property>
        <property name="sheng6" type="java.lang.String">
            <column name="sheng6" length="10">            
            </column>
        </property>
        <property name="sheng7" type="java.lang.String">
            <column name="sheng7" length="200">               
            </column>
        </property>
        <property name="sheng8" type="java.lang.String">
            <column name="sheng8" length="10">             
            </column>
        </property>
        <property name="sheng9" type="java.lang.String">
            <column name="sheng9" length="60">              
            </column>
        </property>
        <property name="sheng10" type="java.lang.String">
            <column name="sheng10" length="60">              
            </column>
        </property>
        <property name="sheng11" type="java.lang.String">
            <column name="sheng11" length="10">              
            </column>
        </property>
        <property name="sheng12" type="java.lang.String">
            <column name="sheng12" length="60">            
            </column>
        </property>
        <property name="sheng13" type="java.lang.String">
            <column name="sheng13" length="60">            
            </column>
        </property>
        <property name="shi1" type="java.lang.String">
            <column name="shi1" length="60">            
            </column>
        </property>
        <property name="shi2" type="java.lang.String">
            <column name="shi2" length="60">            
            </column>
        </property>
		<property name="shi3" type="java.lang.String">
            <column name="shi3" length="60">            
            </column>
        </property>
        <property name="shi4" type="java.lang.String">
            <column name="shi4" length="60">            
            </column>
        </property>
        <property name="shi5" type="java.lang.String">
            <column name="shi5" length="60">            
            </column>
        </property>
        <property name="shi6" type="java.lang.String">
            <column name="shi6" length="60">            
            </column>
        </property>
        <property name="shi7" type="java.lang.String">
            <column name="shi7" length="60">            
            </column>
        </property>
        <property name="shi8" type="java.lang.String">
            <column name="shi8" length="60">            
            </column>
        </property>
        <property name="shi9" type="java.lang.String">
            <column name="shi9" length="60">            
            </column>
        </property>
        <property name="shi10" type="java.lang.String">
            <column name="shi10" length="60">            
            </column>
        </property>
        <property name="shi11" type="java.lang.String">
            <column name="shi11" length="60">            
            </column>
        </property>
        <property name="shi12" type="java.lang.String">
            <column name="shi12" length="60">            
            </column>
        </property>
        <property name="shi13" type="java.lang.String">
            <column name="shi13" length="60">            
            </column>
        </property>
        <property name="shi14" type="java.lang.String">
            <column name="shi14" length="60">            
            </column>
        </property>
        <property name="shi15" type="java.lang.String">
            <column name="shi15" length="60">            
            </column>
        </property>       
        <property name="shi16" type="java.lang.String">
            <column name="shi16" length="60">            
            </column>
        </property>
        <property name="shi17" type="java.lang.String">
            <column name="shi17" length="60">            
            </column>
        </property>
        <property name="shi18" type="java.lang.String">
            <column name="shi18" length="60">            
            </column>
        </property>
        <property name="shi19" type="java.lang.String">
            <column name="shi19" length="60">            
            </column>
        </property>
        <property name="shi20" type="java.lang.String">
            <column name="shi20" length="60">            
            </column>
        </property>
        <property name="shi21" type="java.lang.String">
            <column name="shi21" length="60">            
            </column>
        </property>
        <property name="shi22" type="java.lang.String">
            <column name="shi22" length="60">            
            </column>
        </property>
        <property name="shi23" type="java.lang.String">
            <column name="shi23" length="60">            
            </column>
        </property>
        <property name="shi24" type="java.lang.String">
            <column name="shi24" length="60">            
            </column>
        </property>
        <property name="shi25" type="java.lang.String">
            <column name="shi25" length="60">            
            </column>
        </property>
        <property name="shi26" type="java.lang.String">
            <column name="shi26" length="60">            
            </column>
        </property>
        <property name="shi27" type="java.lang.String">
            <column name="shi27" length="60">            
            </column>
        </property>
        <property name="shi28" type="java.lang.String">
            <column name="shi28" length="60">            
            </column>
        </property>
        <property name="shi29" type="java.lang.String">
            <column name="shi29" length="60">            
            </column>
        </property>       
        <property name="shi30" type="java.lang.String">
            <column name="shi30" length="60">            
            </column>
        </property>
        <property name="shi31" type="java.lang.String">
            <column name="shi31" length="60">            
            </column>
        </property>        
        <property name="shi32" type="java.lang.String">
            <column name="shi32" length="60">            
            </column>
        </property>
        <property name="shi33" type="java.lang.String">
            <column name="shi33" length="60">            
            </column>
        </property>
        <property name="shi34" type="java.lang.String">
            <column name="shi34" length="60">            
            </column>
        </property>
        <property name="shi35" type="java.lang.String">
            <column name="shi35" length="60">            
            </column>
        </property>       
        <property name="shi36" type="java.lang.String">
            <column name="shi36" length="60">            
            </column>
        </property>
        <property name="shi37" type="java.lang.String">
            <column name="shi37" length="60">            
            </column>
        </property>
        <property name="shi38" type="java.lang.String">
            <column name="shi38" length="60">            
            </column>
        </property>
		<property name="shi39" type="java.lang.String">
            <column name="shi39" length="60">            
            </column>
        </property>
        <property name="shi40" type="java.lang.String">
            <column name="shi40" length="60">            
            </column>
        </property>
        <property name="shi41" type="java.lang.String">
            <column name="shi41" length="60">            
            </column>
        </property>
        <property name="shi42" type="java.lang.String">
            <column name="shi42" length="60">            
            </column>
        </property>
        <property name="shi43" type="java.lang.String">
            <column name="shi43" length="60">            
            </column>
        </property>
        <property name="shi44" type="java.lang.String">
            <column name="shi44" length="60">            
            </column>
        </property>
        <property name="shi45" type="java.lang.String">
            <column name="shi45" length="60">            
            </column>
        </property>
        <property name="shi46" type="java.lang.String">
            <column name="shi46" length="60">            
            </column>
        </property>
        <property name="shi47" type="java.lang.String">
            <column name="shi47" length="60">            
            </column>
        </property>
        <property name="shi48" type="java.lang.String">
            <column name="shi48" length="60">            
            </column>
        </property>
        <property name="shi49" type="java.lang.String">
            <column name="shi49" length="60">            
            </column>
        </property>
        <property name="shi50" type="java.lang.String">
            <column name="shi50" length="60">            
            </column>
        </property>
        <property name="shi51" type="java.lang.String">
            <column name="shi51" length="60">            
            </column>
        </property>       
        <property name="shi52" type="java.lang.String">
            <column name="shi52" length="60">            
            </column>
        </property>
        <property name="shi53" type="java.lang.String">
            <column name="shi53" length="60">            
            </column>
        </property>
        <property name="shi54" type="java.lang.String">
            <column name="shi54" length="60">            
            </column>
        </property>
        <property name="shi55" type="java.lang.String">
            <column name="shi55" length="60">            
            </column>
        </property>
        <property name="shi56" type="java.lang.String">
            <column name="shi56" length="60">            
            </column>
        </property>
        <property name="shi57" type="java.lang.String">
            <column name="shi57" length="60">            
            </column>
        </property>
        <property name="shi58" type="java.lang.String">
            <column name="shi58" length="60">            
            </column>
        </property>
        <property name="shi59" type="java.lang.String">
            <column name="shi59" length="60">            
            </column>
        </property>
        <property name="shi60" type="java.lang.String">
            <column name="shi60" length="60">            
            </column>
        </property>
        <property name="shi61" type="java.lang.String">
            <column name="shi61" length="60">            
            </column>
        </property>
        <property name="shi62" type="java.lang.String">
            <column name="shi62" length="60">            
            </column>
        </property>
        <property name="shi63" type="java.lang.String">
            <column name="shi63" length="60">            
            </column>
        </property>
        <property name="shi64" type="java.lang.String">
            <column name="shi64" length="60">            
            </column>
        </property>
        <property name="shi65" type="java.lang.String">
            <column name="shi65" length="60">            
            </column>
        </property>       
        <property name="shi66" type="java.lang.String">
            <column name="shi66" length="60">            
            </column>
        </property>
        <property name="shi67" type="java.lang.String">
            <column name="shi67" length="60">            
            </column>
        </property>        
        <property name="shi68" type="java.lang.String">
            <column name="shi68" length="60">            
            </column>
        </property>
        <property name="shi69" type="java.lang.String">
            <column name="shi69" length="60">            
            </column>
        </property>
        <property name="shi70" type="java.lang.String">
            <column name="shi70" length="60">            
            </column>
        </property>
        <property name="shi71" type="java.lang.String">
            <column name="shi71" length="60">            
            </column>
        </property>       
        <property name="shi72" type="java.lang.String">
            <column name="shi72" length="60">            
            </column>
        </property>
      
        <property name="shi73" type="java.lang.String">
            <column name="shi73" length="60">            
            </column>
        </property>
        <property name="shi74" type="java.lang.String">
            <column name="shi74" length="60">            
            </column>
        </property>
		<property name="shi75" type="java.lang.String">
            <column name="shi75" length="60">            
            </column>
        </property>
        <property name="shi76" type="java.lang.String">
            <column name="shi76" length="60">            
            </column>
        </property>
        <property name="shi77" type="java.lang.String">
            <column name="shi77" length="60">            
            </column>
        </property>
        <property name="shi78" type="java.lang.String">
            <column name="shi78" length="60">            
            </column>
        </property>
        <property name="shi79" type="java.lang.String">
            <column name="shi79" length="60">            
            </column>
        </property>
        <property name="shi80" type="java.lang.String">
            <column name="shi80" length="60">            
            </column>
        </property>
        <property name="shi81" type="java.lang.String">
            <column name="shi81" length="60">            
            </column>
        </property>
        <property name="shi82" type="java.lang.String">
            <column name="shi82" length="60">            
            </column>
        </property>
        <property name="shi83" type="java.lang.String">
            <column name="shi83" length="60">            
            </column>
        </property>
        <property name="shi84" type="java.lang.String">
            <column name="shi84" length="60">            
            </column>
        </property>
        <property name="shi85" type="java.lang.String">
            <column name="shi85" length="60">            
            </column>
        </property>
        <property name="shi86" type="java.lang.String">
            <column name="shi86" length="60">            
            </column>
        </property>
        <property name="shi87" type="java.lang.String">
            <column name="shi87" length="60">            
            </column>
        </property>       
        <property name="shi88" type="java.lang.String">
            <column name="shi88" length="60">            
            </column>
        </property>
        <property name="shi89" type="java.lang.String">
            <column name="shi89" length="60">            
            </column>
        </property>
        <property name="shi90" type="java.lang.String">
            <column name="shi90" length="60">            
            </column>
        </property>
        <property name="shi91" type="java.lang.String">
            <column name="shi91" length="60">            
            </column>
        </property>
        <property name="shi92" type="java.lang.String">
            <column name="shi92" length="60">            
            </column>
        </property>
        <property name="shi93" type="java.lang.String">
            <column name="shi93" length="60">            
            </column>
        </property>
        <property name="shi94" type="java.lang.String">
            <column name="shi94" length="60">            
            </column>
        </property>
        <property name="shi95" type="java.lang.String">
            <column name="shi95" length="60">            
            </column>
        </property>
        <property name="shi96" type="java.lang.String">
            <column name="shi96" length="60">            
            </column>
        </property>
        <property name="shi97" type="java.lang.String">
            <column name="shi97" length="60">            
            </column>
        </property>
        <property name="shi98" type="java.lang.String">
            <column name="shi98" length="60">            
            </column>
        </property>
        <property name="shi99" type="java.lang.String">
            <column name="shi99" length="60">            
            </column>
        </property>
        <property name="shi100" type="java.lang.String">
            <column name="shi100" length="60">            
            </column>
        </property>
        <property name="shi101" type="java.lang.String">
            <column name="shi101" length="60">            
            </column>
        </property>       
        <property name="shi102" type="java.lang.String">
            <column name="shi102" length="60">            
            </column>
        </property>
        <property name="shi103" type="java.lang.String">
            <column name="shi103" length="60">            
            </column>
        </property>        
        <property name="shi104" type="java.lang.String">
            <column name="shi104" length="60">            
            </column>
        </property>
        <property name="shi105" type="java.lang.String">
            <column name="shi105" length="60">            
            </column>
        </property>
        <property name="shi106" type="java.lang.String">
            <column name="shi106" length="60">            
            </column>
        </property>
        <property name="shi107" type="java.lang.String">
            <column name="shi107" length="60">            
            </column>
        </property>       
        <property name="shi108" type="java.lang.String">
            <column name="shi108" length="60">            
            </column>
        </property>

        <property name="shi109" type="java.lang.String">
            <column name="shi109" length="60">            
            </column>
        </property>
        <property name="shi110" type="java.lang.String">
            <column name="shi110" length="60">            
            </column>
        </property>
        <property name="shi111" type="java.lang.String">
            <column name="shi111" length="60">            
            </column>
        </property>
        <property name="shi112" type="java.lang.String">
            <column name="shi112" length="60">            
            </column>
        </property>
        <property name="shi113" type="java.lang.String">
            <column name="shi113" length="60">            
            </column>
        </property>       
        <property name="shi114" type="java.lang.String">
            <column name="shi114" length="60">            
            </column>
        </property>
        <property name="shi115" type="java.lang.String">
            <column name="shi115" length="60">            
            </column>
        </property>
        <property name="shi116" type="java.lang.String">
            <column name="shi116" length="60">            
            </column>
        </property>
        <property name="shi117" type="java.lang.String">
            <column name="shi117" length="60">            
            </column>
        </property>
        <property name="shi118" type="java.lang.String">
            <column name="shi118" length="60">            
            </column>
        </property>
        <property name="shi119" type="java.lang.String">
            <column name="shi119" length="60">            
            </column>
        </property>
        <property name="shi120" type="java.lang.String">
            <column name="shi120" length="60">            
            </column>
        </property>
        <property name="shi121" type="java.lang.String">
            <column name="shi121" length="60">            
            </column>
        </property>
        <property name="shi122" type="java.lang.String">
            <column name="shi122" length="60">            
            </column>
        </property>
        <property name="shi123" type="java.lang.String">
            <column name="shi123" length="60">            
            </column>
        </property>
        <property name="shi124" type="java.lang.String">
            <column name="shi124" length="60">            
            </column>
        </property>
        <property name="shi125" type="java.lang.String">
            <column name="shi125" length="60">            
            </column>
        </property>
        <property name="shi126" type="java.lang.String">
            <column name="shi126" length="60">            
            </column>
        </property>
        <property name="shi127" type="java.lang.String">
            <column name="shi127" length="60">            
            </column>
        </property>       
        <property name="shi128" type="java.lang.String">
            <column name="shi128" length="60">            
            </column>
        </property>
        <property name="shi129" type="java.lang.String">
            <column name="shi129" length="60">            
            </column>
        </property>        
        <property name="shi130" type="java.lang.String">
            <column name="shi130" length="60">            
            </column>
        </property>
        <property name="shi131" type="java.lang.String">
            <column name="shi131" length="60">            
            </column>
        </property>
        <property name="shi132" type="java.lang.String">
            <column name="shi132" length="60">            
            </column>
        </property>
        <property name="shi133" type="java.lang.String">
            <column name="shi133" length="60">            
            </column>
        </property>       
        <property name="shi134" type="java.lang.String">
            <column name="shi134" length="60">            
            </column>
        </property>
        
        <property name="shihou1" type="java.lang.String">
            <column name="shihou1" length="60">            
            </column>
        </property>
        <property name="shihou2" type="java.lang.String">
            <column name="shihou2" length="60">            
            </column>
        </property>
        <property name="shihou3" type="java.lang.String">
            <column name="shihou3" length="60">            
            </column>
        </property>
        <property name="shihou4" type="java.lang.String">
            <column name="shihou4" length="60">            
            </column>
        </property>
        <property name="shihou5" type="java.lang.String">
            <column name="shihou5" length="60">            
            </column>
        </property>
        <property name="shihou6" type="java.lang.String">
            <column name="shihou6" length="60">            
            </column>
        </property>
        <property name="shihou7" type="java.lang.String">
            <column name="shihou7" length="60">            
            </column>
        </property>
        <property name="shihou8" type="java.lang.String">
            <column name="shihou8" length="60">            
            </column>
        </property>
        <property name="shihou9" type="java.lang.String">
            <column name="shihou9" length="60">            
            </column>
        </property>
        <property name="shihou10" type="java.lang.String">
            <column name="shihou10" length="60">            
            </column>
        </property>
        <property name="shihou11" type="java.lang.String">
            <column name="shihou11" length="60">            
            </column>
        </property>
        <property name="shihou12" type="java.lang.String">
            <column name="shihou12" length="60">            
            </column>
        </property>
        <property name="shihou13" type="java.lang.String">
            <column name="shihou13" length="60">            
            </column>
        </property>
        <property name="shihou14" type="java.lang.String">
            <column name="shihou14" length="60">            
            </column>
        </property>
        <property name="shihou15" type="java.lang.String">
            <column name="shihou15" length="60">            
            </column>
        </property>
        <property name="shihou16" type="java.lang.String">
            <column name="shihou16" length="60">            
            </column>
        </property>
        <property name="shihou17" type="java.lang.String">
            <column name="shihou17" length="60">            
            </column>
        </property>
        <property name="shihou18" type="java.lang.String">
            <column name="shihou18" length="60">            
            </column>
        </property>
        <property name="shihou19" type="java.lang.String">
            <column name="shihou19" length="60">            
            </column>
        </property>
        <property name="shihou20" type="java.lang.String">
            <column name="shihou20" length="60">            
            </column>
        </property>
        <property name="shihou21" type="java.lang.String">
            <column name="shihou21" length="60">            
            </column>
        </property>
        <property name="shihou22" type="java.lang.String">
            <column name="shihou22" length="60">            
            </column>
        </property>
        <property name="shihou23" type="java.lang.String">
            <column name="shihou23" length="60">            
            </column>
        </property>
        <property name="shihou24" type="java.lang.String">
            <column name="shihou24" length="60">            
            </column>
        </property>
        <property name="shihou25" type="java.lang.String">
            <column name="shihou25" length="60">            
            </column>
        </property>
        <property name="shihou26" type="java.lang.String">
            <column name="shihou26" length="60">            
            </column>
        </property>
        <property name="shihou27" type="java.lang.String">
            <column name="shihou27" length="60">            
            </column>
        </property>
        <property name="shihou28" type="java.lang.String">
            <column name="shihou28" length="60">            
            </column>
        </property>
        <property name="shihou29" type="java.lang.String">
            <column name="shihou29" length="60">            
            </column>
        </property>
        <property name="shihou30" type="java.lang.String">
            <column name="shihou30" length="60">            
            </column>
        </property>
        <property name="shihou31" type="java.lang.String">
            <column name="shihou31" length="60">            
            </column>
        </property>
        <property name="shihou32" type="java.lang.String">
            <column name="shihou32" length="60">            
            </column>
        </property>
        <property name="shihou33" type="java.lang.String">
            <column name="shihou33" length="60">            
            </column>
        </property>
        <property name="shihou34" type="java.lang.String">
            <column name="shihou34" length="60">            
            </column>
        </property>
        <property name="shihou35" type="java.lang.String">
            <column name="shihou35" length="60">            
            </column>
        </property>
        <property name="shihou36" type="java.lang.String">
            <column name="shihou36" length="60">            
            </column>
        </property>
        <property name="shihou37" type="java.lang.String">
            <column name="shihou37" length="60">            
            </column>
        </property>
        <property name="shihou38" type="java.lang.String">
            <column name="shihou38" length="60">            
            </column>
        </property>
        <property name="shihou39" type="java.lang.String">
            <column name="shihou39" length="60">            
            </column>
        </property>
        <property name="shihou40" type="java.lang.String">
            <column name="shihou40" length="60">            
            </column>
        </property>
        <property name="shihou41" type="java.lang.String">
            <column name="shihou41" length="60">            
            </column>
        </property>
        <property name="shihou42" type="java.lang.String">
            <column name="shihou42" length="60">            
            </column>
        </property>
        <property name="shihou43" type="java.lang.String">
            <column name="shihou43" length="60">            
            </column>
        </property>
        <property name="shihou44" type="java.lang.String">
            <column name="shihou44" length="60">            
            </column>
        </property>
        <property name="shihou45" type="java.lang.String">
            <column name="shihou45" length="60">            
            </column>
        </property>
        <property name="shihou46" type="java.lang.String">
            <column name="shihou46" length="60">            
            </column>
        </property>
        <property name="shihou47" type="java.lang.String">
            <column name="shihou47" length="60">            
            </column>
        </property>
        <property name="shihou48" type="java.lang.String">
            <column name="shihou48" length="60">            
            </column>
        </property>
        <property name="shihou49" type="java.lang.String">
            <column name="shihou49" length="60">            
            </column>
        </property>
        <property name="shihou50" type="java.lang.String">
            <column name="shihou50" length="60">            
            </column>
        </property>
        <property name="shihou51" type="java.lang.String">
            <column name="shihou51" length="60">            
            </column>
        </property>
        <property name="shihou52" type="java.lang.String">
            <column name="shihou52" length="60">            
            </column>
        </property>

       <property name="jd1" type="java.lang.String">
            <column name="jd1" length="60">            
            </column>
        </property>
        <property name="jd2" type="java.lang.String">
            <column name="jd2" length="60">            
            </column>
        </property>
        <property name="jd3" type="java.lang.String">
            <column name="jd3" length="60">            
            </column>
        </property>
        <property name="jd4" type="java.lang.String">
            <column name="jd4" length="60">            
            </column>
        </property>
        <property name="jd5" type="java.lang.String">
            <column name="jd5" length="60">            
            </column>
        </property>
        <property name="jd6" type="java.lang.String">
            <column name="jd6" length="60">            
            </column>
        </property>
        <property name="jd7" type="java.lang.String">
            <column name="jd7" length="60">            
            </column>
        </property>
        <property name="jd8" type="java.lang.String">
            <column name="jd8" length="60">            
            </column>
        </property>
        <property name="jd9" type="java.lang.String">
            <column name="jd9" length="60">            
            </column>
        </property>
        <property name="jd10" type="java.lang.String">
            <column name="jd10" length="60">            
            </column>
        </property>
        <property name="jd11" type="java.lang.String">
            <column name="jd11" length="60">            
            </column>
        </property>
       
       <property name="ldbywy1" type="java.lang.String">
            <column name="ldbywy1" length="60">            
            </column>
        </property>
        <property name="ldbywy2" type="java.lang.String">
            <column name="ldbywy2" length="60">            
            </column>
        </property>
        <property name="ldbywy3" type="java.lang.String">
            <column name="ldbywy3" length="60">            
            </column>
        </property>
        <property name="ldbywy4" type="java.lang.String">
            <column name="ldbywy4" length="60">            
            </column>
        </property>
        <property name="ldbywy5" type="java.lang.String">
            <column name="ldbywy5" length="60">            
            </column>
        </property>
        <property name="ldbywy6" type="java.lang.String">
            <column name="ldbywy6" length="60">            
            </column>
        </property>
        <property name="ldbywy7" type="java.lang.String">
            <column name="ldbywy7" length="60">            
            </column>
        </property>
        <property name="ldbywy8" type="java.lang.String">
            <column name="ldbywy8" length="60">            
            </column>
        </property>
        <property name="ldbywy9" type="java.lang.String">
            <column name="ldbywy9" length="60">            
            </column>
        </property>
        <property name="ldbywy10" type="java.lang.String">
            <column name="ldbywy10" length="60">            
            </column>
        </property>
        <property name="ldbywy11" type="java.lang.String">
            <column name="ldbywy11" length="60">            
            </column>
        </property>
        <property name="ldbywy12" type="java.lang.String">
            <column name="ldbywy12" length="60">            
            </column>
        </property>
        <property name="ldbywy13" type="java.lang.String">
            <column name="ldbywy13" length="60">            
            </column>
        </property>
        <property name="ldbywy14" type="java.lang.String">
            <column name="ldbywy14" length="60">            
            </column>
        </property>
        <property name="ldbywy15" type="java.lang.String">
            <column name="ldbywy15" length="60">            
            </column>
        </property>
        <property name="ldbywy16" type="java.lang.String">
            <column name="ldbywy16" length="60">            
            </column>
        </property>
       
    </class>
</hibernate-mapping>
